respond_admin/__init__.py
respond_admin/tests.py
respond_admin/mixins/__init__.py
respond_admin/mixins/drug_supply_inline_mixin.py
respond_admin/mixins/medical_adherence_admin_mixin.py
respond_forms/__init__.py
respond_forms/utils.py
respond_forms/form_validator_mixins/__init__.py
respond_forms/form_validator_mixins/blood_results_form_validator_mixin.py
respond_forms/form_validator_mixins/bp_form_validator_mixin.py
respond_forms/form_validator_mixins/crf_form_validator_mixin.py
respond_forms/form_validator_mixins/diagnosis_form_validator_mixin.py
respond_forms/form_validator_mixins/drug_refill_form_validator_mixin.py
respond_forms/form_validator_mixins/hiv_initial_review_form_validator.py
respond_forms/form_validator_mixins/initial_review_form_validator_mixin.py
respond_forms/form_validator_mixins/medication_adherence_form_validator_mixin.py
respond_forms/form_validator_mixins/result_form_validator_mixin.py
respond_forms/form_validator_mixins/review_form_validator_mixin.py
respond_forms/form_validators/__init__.py
respond_forms/form_validators/blood_results_form_validator.py
respond_forms/form_validators/glucose_form_validator.py
respond_forms/mixins/__init__.py
respond_forms/mixins/drug_supply_ncd_form_mixin.py
respond_forms/tests/__init__.py
respond_forms/tests/test_glucose.py
respond_models/__init__.py
respond_models/apps.py
respond_models/choices.py
respond_models/constants.py
respond_models/diagnoses.py
respond_models/stubs.py
respond_models/utils.py
respond_models/mixins/__init__.py
respond_models/mixins/creatinine_fields_model_mixin.py
respond_models/mixins/drug_refill_model_mixin.py
respond_models/mixins/drug_supply_model_mixin.py
respond_models/mixins/eq_5d.py
respond_models/mixins/medication.py
respond_models/mixins/medication_adherence.py
respond_models/mixins/phq9.py
respond_models/mixins/review.py
respond_models/mixins/sf12_model_mixin.py
respond_models/mixins/ae/__init__.py
respond_models/mixins/ae/death_report.py
respond_africa-0.1.13.dist-info/LICENSE
respond_africa-0.1.13.dist-info/METADATA
respond_africa-0.1.13.dist-info/WHEEL
respond_africa-0.1.13.dist-info/top_level.txt
respond_africa-0.1.13.dist-info/RECORD
